data401_nlp/__init__.py
data401_nlp/_modidx.py
data401_nlp/helpers/__init__.py
data401_nlp/helpers/env.py
data401_nlp/helpers/llm.py
data401_nlp/helpers/spacy.py
data401_nlp/helpers/submit.py
data401_nlp/tests/__init__.py
data401_nlp/tests/platform.py
data401_nlp-0.0.6.dist-info/licenses/LICENSE
data401_nlp-0.0.6.dist-info/METADATA
data401_nlp-0.0.6.dist-info/WHEEL
data401_nlp-0.0.6.dist-info/entry_points.txt
data401_nlp-0.0.6.dist-info/top_level.txt
data401_nlp-0.0.6.dist-info/RECORD
