Metadata-Version: 2.4
Name: data401-nlp
Version: 0.0.6
Summary: Interactive NLP course labs for Jupyter, Colab, and Deepnote
Home-page: https://github.com/su-dataAI/data401-nlp
Author: Lisa D Harper
Author-email: Lisa D Harper <lisa.harper@su.edu>
License: Apache-2.0
Project-URL: Homepage, https://github.com/su-dataAI/data401-nlp
Project-URL: Documentation, https://su-dataAI.github.io/data401-nlp
Project-URL: Repository, https://github.com/su-dataAI/data401-nlp
Project-URL: Bug Tracker, https://github.com/su-dataAI/data401-nlp/issues
Project-URL: Course Website, https://www.notion.so/Intro-to-Natural-Language-Processing-28b213a83886806982a5c03b425595c4
Keywords: nbdev,jupyter,nlp,education,spacy,transformers
Classifier: Development Status :: 4 - Beta
Classifier: Intended Audience :: Developers
Classifier: Intended Audience :: Education
Classifier: License :: OSI Approved :: Apache Software License
Classifier: Natural Language :: English
Classifier: Programming Language :: Python :: 3.11
Classifier: Programming Language :: Python :: 3.12
Classifier: Topic :: Scientific/Engineering :: Artificial Intelligence
Classifier: Topic :: Education
Requires-Python: >=3.11
License-File: LICENSE
Requires-Dist: fastcore>=1.8.16
Requires-Dist: nbformat>=5.0
Requires-Dist: python-dotenv>=1.2.1
Requires-Dist: httpx>=0.27.0
Requires-Dist: lisette>=0.0.15
Requires-Dist: dialoghelper>=0.1.6
Requires-Dist: spacy<3.9,>=3.7
Provides-Extra: dev
Requires-Dist: pytest>=7.0; extra == "dev"
Requires-Dist: nbdev>=2.3.0; extra == "dev"
Provides-Extra: nlp
Requires-Dist: spacy<3.9,>=3.7; extra == "nlp"
Requires-Dist: nltk<3.10,>=3.9; extra == "nlp"
Provides-Extra: transformers
Requires-Dist: transformers<4.50,>=4.45; extra == "transformers"
Requires-Dist: torch<2.5,>=2.1; extra == "transformers"
Provides-Extra: api
Requires-Dist: fastapi<0.128,>=0.100; extra == "api"
Requires-Dist: pydantic<3,>=2.0; extra == "api"
Provides-Extra: all
Requires-Dist: spacy<3.9,>=3.7; extra == "all"
Requires-Dist: nltk<3.10,>=3.9; extra == "all"
Requires-Dist: transformers<4.50,>=4.45; extra == "all"
Requires-Dist: torch<2.5,>=2.1; extra == "all"
Requires-Dist: fastapi<0.128,>=0.100; extra == "all"
Requires-Dist: pydantic<3,>=2.0; extra == "all"
Dynamic: author
Dynamic: home-page
Dynamic: license-file
Dynamic: requires-dist
Dynamic: requires-python
